aog/__init__.py
aog/conv.py
aog-1.0.3.dist-info/METADATA
aog-1.0.3.dist-info/RECORD
aog-1.0.3.dist-info/WHEEL
aog-1.0.3.dist-info/top_level.txt
